{ "type": "FeatureCollection", "features": [{"type": "Feature", "geometry": { "type": "Point", "coordinates": [-76.976134,39.563822]}, "properties": { "type": 1, "address":"Jermor Ln / Malcolm Dr"}},{"type": "Feature", "geometry": { "type": "Point", "coordinates": [-78.512163,40.051616]}, "properties": { "type": 5, "address":""}},{"type": "Feature", "geometry": { "type": "Point", "coordinates": [-78.252461,39.989599]}, "properties": { "type": 5, "address":""}},{"type": "Feature", "geometry": { "type": "Point", "coordinates": [-77.813287,40.094176]}, "properties": { "type": 5, "address":""}},{"type": "Feature", "geometry": { "type": "Point", "coordinates": [-77.612915,40.15349]}, "properties": { "type": 5, "address":""}},{"type": "Feature", "geometry": { "type": "Point", "coordinates": [-77.151532,40.229382]}, "properties": { "type": 5, "address":""}},{"type": "Feature", "geometry": { "type": "Point", "coordinates": [-76.976266,40.197495]}, "properties": { "type": 5, "address":""}},{"type": "Feature", "geometry": { "type": "Point", "coordinates": [-77.96083,40.051115]}, "properties": { "type": 5, "address":""}},{"type": "Feature", "geometry": { "type": "Point", "coordinates": [-76.876144,40.210704]}, "properties": { "type": 5, "address":""}},{"type": "Feature", "geometry": { "type": "Point", "coordinates": [-79.081972,40.019021]}, "properties": { "type": 5, "address":""}},{"type": "Feature", "geometry": { "type": "Point", "coordinates": [-76.78688,40.217029]}, "properties": { "type": 5, "address":""}}]}