{ "type": "FeatureCollection", "features": [{"type": "Feature", "geometry": { "type": "Point", "coordinates": [-96.374447,42.48987]}, "properties": { "type": 1, "address":"S Fairmount St / Gordon Dr"}},{"type": "Feature", "geometry": { "type": "Point", "coordinates": [-96.345744,42.475879]}, "properties": { "type": 1, "address":"E Gordon Dr / S Palmetto St"}},{"type": "Feature", "geometry": { "type": "Point", "coordinates": [-96.396395,42.495295]}, "properties": { "type": 1, "address":"5th St / Court St"}},{"type": "Feature", "geometry": { "type": "Point", "coordinates": [-96.361295,42.529859]}, "properties": { "type": 1, "address":"US Hwy 75 Bus / Smith River Rd"}},{"type": "Feature", "geometry": { "type": "Point", "coordinates": [-96.34647,42.44736]}, "properties": { "type": 1, "address":"S Lakeport St / Sergeant Rd"}}]}