{ "type": "FeatureCollection", "features": [{"type": "Feature", "geometry": { "type": "Point", "coordinates": [-76.083455,40.214632]}, "properties": { "type": 5, "address":""}},{"type": "Feature", "geometry": { "type": "Point", "coordinates": [-75.882633,40.16157]}, "properties": { "type": 5, "address":""}},{"type": "Feature", "geometry": { "type": "Point", "coordinates": [-75.534943,40.072027]}, "properties": { "type": 5, "address":""}},{"type": "Feature", "geometry": { "type": "Point", "coordinates": [-75.403296,40.08786]}, "properties": { "type": 5, "address":""}},{"type": "Feature", "geometry": { "type": "Point", "coordinates": [-75.285938,40.108065]}, "properties": { "type": 5, "address":""}},{"type": "Feature", "geometry": { "type": "Point", "coordinates": [-76.436262,40.232527]}, "properties": { "type": 5, "address":""}},{"type": "Feature", "geometry": { "type": "Point", "coordinates": [-75.669154,40.065997]}, "properties": { "type": 5, "address":""}},{"type": "Feature", "geometry": { "type": "Point", "coordinates": [-75.287152,40.109611]}, "properties": { "type": 5, "address":""}},{"type": "Feature", "geometry": { "type": "Point", "coordinates": [-76.103067,39.581944]}, "properties": { "type": 5, "address":""}},{"type": "Feature", "geometry": { "type": "Point", "coordinates": [-75.447971,39.686246]}, "properties": { "type": 5, "address":""}},{"type": "Feature", "geometry": { "type": "Point", "coordinates": [-76.354457,39.52634]}, "properties": { "type": 1, "address":"State Hwy 24 / Baltimore Pike"}},{"type": "Feature", "geometry": { "type": "Point", "coordinates": [-76.347675,39.533361]}, "properties": { "type": 1, "address":"Fulford Ave / S Bond St"}},{"type": "Feature", "geometry": { "type": "Point", "coordinates": [-75.741311,39.605825]}, "properties": { "type": 1, "address":"S College Ave / Pulaski Hwy"}},{"type": "Feature", "geometry": { "type": "Point", "coordinates": [-75.735872,39.67856]}, "properties": { "type": 1, "address":"Wyoming Rd / Library Ave"}},{"type": "Feature", "geometry": { "type": "Point", "coordinates": [-75.715368,39.608162]}, "properties": { "type": 1, "address":"Wrangle Hill Rd / Pulaski Hwy"}},{"type": "Feature", "geometry": { "type": "Point", "coordinates": [-75.658224,39.72378]}, "properties": { "type": 1, "address":"Limestone Rd / Kirkwood Hwy"}},{"type": "Feature", "geometry": { "type": "Point", "coordinates": [-75.581697,39.741433]}, "properties": { "type": 1, "address":"Wilmington Ave / Prospect Rd"}},{"type": "Feature", "geometry": { "type": "Point", "coordinates": [-75.57663,39.743914]}, "properties": { "type": 1, "address":"S Union St / Maple St"}},{"type": "Feature", "geometry": { "type": "Point", "coordinates": [-75.573004,39.749249]}, "properties": { "type": 1, "address":"N Union St / W 4th St"}},{"type": "Feature", "geometry": { "type": "Point", "coordinates": [-75.544288,39.828809]}, "properties": { "type": 1, "address":"Naamans Rd / Concord Pike"}},{"type": "Feature", "geometry": { "type": "Point", "coordinates": [-75.538525,39.742944]}, "properties": { "type": 1, "address":"E 11th St / N Church St"}},{"type": "Feature", "geometry": { "type": "Point", "coordinates": [-75.520619,39.689127]}, "properties": { "type": 5, "address":""}},{"type": "Feature", "geometry": { "type": "Point", "coordinates": [-75.276962,39.755393]}, "properties": { "type": 5, "address":""}},{"type": "Feature", "geometry": { "type": "Point", "coordinates": [-75.236697,39.894648]}, "properties": { "type": 1, "address":"Bartram Ave / Island Ave"}},{"type": "Feature", "geometry": { "type": "Point", "coordinates": [-75.205598,40.028653]}, "properties": { "type": 1, "address":"Henry Ave / W Walnut Ln"}},{"type": "Feature", "geometry": { "type": "Point", "coordinates": [-75.129588,40.148811]}, "properties": { "type": 1, "address":"W Moreland Rd / Fitzwatertown Rd"}},{"type": "Feature", "geometry": { "type": "Point", "coordinates": [-75.121808,40.114567]}, "properties": { "type": 1, "address":"York Rd / Susquehanna Rd"}},{"type": "Feature", "geometry": { "type": "Point", "coordinates": [-75.110005,40.039151]}, "properties": { "type": 1, "address":"Rising Sun Ave / Adams Ave"}},{"type": "Feature", "geometry": { "type": "Point", "coordinates": [-75.05408,40.044324]}, "properties": { "type": 1, "address":"Cottman Ave / Roosevelt Blvd"}},{"type": "Feature", "geometry": { "type": "Point", "coordinates": [-75.028645,40.080853]}, "properties": { "type": 1, "address":"Grant Ave / Roosevelt Blvd"}},{"type": "Feature", "geometry": { "type": "Point", "coordinates": [-74.987859,40.114196]}, "properties": { "type": 1, "address":"Southampton Rd / Roosevelt Blvd"}},{"type": "Feature", "geometry": { "type": "Point", "coordinates": [-74.969115,40.133075]}, "properties": { "type": 5, "address":""}},{"type": "Feature", "geometry": { "type": "Point", "coordinates": [-74.819096,40.025949]}, "properties": { "type": 5, "address":""}},{"type": "Feature", "geometry": { "type": "Point", "coordinates": [-74.303555,40.484338]}, "properties": { "type": 5, "address":""}},{"type": "Feature", "geometry": { "type": "Point", "coordinates": [-74.207974,40.755281]}, "properties": { "type": 5, "address":""}},{"type": "Feature", "geometry": { "type": "Point", "coordinates": [-74.195978,40.635381]}, "properties": { "type": 5, "address":""}},{"type": "Feature", "geometry": { "type": "Point", "coordinates": [-74.18407,40.602664]}, "properties": { "type": 1, "address":"South Ave / Travis Ave"}},{"type": "Feature", "geometry": { "type": "Point", "coordinates": [-74.156702,40.616406]}, "properties": { "type": 1, "address":"Richmond Ave / W Caswell Ave"}},{"type": "Feature", "geometry": { "type": "Point", "coordinates": [-74.09808,40.610959]}, "properties": { "type": 1, "address":"Narrows Rd N / Clove Rd"}},{"type": "Feature", "geometry": { "type": "Point", "coordinates": [-74.070208,40.586563]}, "properties": { "type": 1, "address":"Father Capodanno Blvd"}},{"type": "Feature", "geometry": { "type": "Point", "coordinates": [-74.070996,40.97965]}, "properties": { "type": 5, "address":""}},{"type": "Feature", "geometry": { "type": "Point", "coordinates": [-74.0655,40.95996]}, "properties": { "type": 5, "address":""}},{"type": "Feature", "geometry": { "type": "Point", "coordinates": [-74.045531,40.606401]}, "properties": { "type": 5, "address":""}},{"type": "Feature", "geometry": { "type": "Point", "coordinates": [-74.009914,40.762491]}, "properties": { "type": 5, "address":""}},{"type": "Feature", "geometry": { "type": "Point", "coordinates": [-74.000677,40.675559]}, "properties": { "type": 1, "address":"W 9th St / Hamilton Ave"}},{"type": "Feature", "geometry": { "type": "Point", "coordinates": [-73.994201,40.771534]}, "properties": { "type": 1, "address":"Joe Dimaggio Hwy / 12th Ave"}},{"type": "Feature", "geometry": { "type": "Point", "coordinates": [-73.980465,40.676406]}, "properties": { "type": 1, "address":"5th Ave / Union St"}},{"type": "Feature", "geometry": { "type": "Point", "coordinates": [-73.97755,40.713244]}, "properties": { "type": 1, "address":"F D R Dr / Grand St"}},{"type": "Feature", "geometry": { "type": "Point", "coordinates": [-73.977203,40.747026]}, "properties": { "type": 1, "address":"E 36th St / 3rd Ave"}},{"type": "Feature", "geometry": { "type": "Point", "coordinates": [-73.972458,40.623958]}, "properties": { "type": 1, "address":"Ave J / Bay Pkwy"}},{"type": "Feature", "geometry": { "type": "Point", "coordinates": [-73.973229,40.795269]}, "properties": { "type": 1, "address":"W 96th St / W End Ave"}},{"type": "Feature", "geometry": { "type": "Point", "coordinates": [-75.726476,39.662675]}, "properties": { "type": 1, "address":"Christina Pkwy / Marrows Rd"}},{"type": "Feature", "geometry": { "type": "Point", "coordinates": [-75.571413,39.758152]}, "properties": { "type": 1, "address":"Pennsylvania Ave / Woodlawn Ave"}},{"type": "Feature", "geometry": { "type": "Point", "coordinates": [-75.555799,39.739464]}, "properties": { "type": 1, "address":"N West St / Lancaster Ave"}},{"type": "Feature", "geometry": { "type": "Point", "coordinates": [-75.550604,39.748952]}, "properties": { "type": 1, "address":"N Washington St / W 12th St"}},{"type": "Feature", "geometry": { "type": "Point", "coordinates": [-75.540928,39.733487]}, "properties": { "type": 1, "address":"S Heald St / Christiana Ave"}},{"type": "Feature", "geometry": { "type": "Point", "coordinates": [-75.150156,40.051568]}, "properties": { "type": 1, "address":"Ogontz Ave / Stenton Ave"}},{"type": "Feature", "geometry": { "type": "Point", "coordinates": [-74.971135,40.087573]}, "properties": { "type": 1, "address":"Woodhaven Rd / Knights Rd"}},{"type": "Feature", "geometry": { "type": "Point", "coordinates": [-74.408233,40.478087]}, "properties": { "type": 5, "address":""}},{"type": "Feature", "geometry": { "type": "Point", "coordinates": [-74.30345,40.485369]}, "properties": { "type": 5, "address":""}},{"type": "Feature", "geometry": { "type": "Point", "coordinates": [-74.247043,40.524753]}, "properties": { "type": 5, "address":""}},{"type": "Feature", "geometry": { "type": "Point", "coordinates": [-74.230692,40.593527]}, "properties": { "type": 5, "address":""}},{"type": "Feature", "geometry": { "type": "Point", "coordinates": [-74.18429,40.805083]}, "properties": { "type": 5, "address":""}},{"type": "Feature", "geometry": { "type": "Point", "coordinates": [-74.176634,40.829698]}, "properties": { "type": 5, "address":""}},{"type": "Feature", "geometry": { "type": "Point", "coordinates": [-74.174468,40.852422]}, "properties": { "type": 5, "address":""}},{"type": "Feature", "geometry": { "type": "Point", "coordinates": [-74.163212,40.592602]}, "properties": { "type": 1, "address":"Richmond Ave / Draper Pl"}},{"type": "Feature", "geometry": { "type": "Point", "coordinates": [-74.108058,40.572139]}, "properties": { "type": 1, "address":"Hylan Blvd / Burbank Ave"}},{"type": "Feature", "geometry": { "type": "Point", "coordinates": [-74.097419,40.61026]}, "properties": { "type": 1, "address":"Clove Rd / Emerson Dr"}},{"type": "Feature", "geometry": { "type": "Point", "coordinates": [-74.018431,40.640828]}, "properties": { "type": 1, "address":"4th Ave / 60th St"}},{"type": "Feature", "geometry": { "type": "Point", "coordinates": [-74.00557,40.633072]}, "properties": { "type": 1, "address":"Fort Hamilton Pkwy / 60th St"}},{"type": "Feature", "geometry": { "type": "Point", "coordinates": [-73.984524,40.696037]}, "properties": { "type": 1, "address":"Flatbush Ave Exn / Tillary St"}},{"type": "Feature", "geometry": { "type": "Point", "coordinates": [-73.987242,40.776028]}, "properties": { "type": 1, "address":"W End Ave / W 66th St"}},{"type": "Feature", "geometry": { "type": "Point", "coordinates": [-73.983737,40.595825]}, "properties": { "type": 1, "address":"86th St / Ave U"}},{"type": "Feature", "geometry": { "type": "Point", "coordinates": [-73.979532,40.739775]}, "properties": { "type": 1, "address":"E 26th St / 2nd Ave"}},{"type": "Feature", "geometry": { "type": "Point", "coordinates": [-73.975932,40.683508]}, "properties": { "type": 1, "address":"Atlantic Ave / Fort Greene Pl"}},{"type": "Feature", "geometry": { "type": "Point", "coordinates": [-76.08231,39.564133]}, "properties": { "type": 5, "address":""}},{"type": "Feature", "geometry": { "type": "Point", "coordinates": [-75.704446,39.611333]}, "properties": { "type": 1, "address":"E Scotland Dr / Pulaski Hwy"}},{"type": "Feature", "geometry": { "type": "Point", "coordinates": [-75.573466,39.746369]}, "properties": { "type": 1, "address":"Lancaster Ave / S Lincoln St"}},{"type": "Feature", "geometry": { "type": "Point", "coordinates": [-75.550425,39.74004]}, "properties": { "type": 1, "address":"E 4th St / N King St"}},{"type": "Feature", "geometry": { "type": "Point", "coordinates": [-75.542494,39.763367]}, "properties": { "type": 1, "address":"N Broom St / Concord Ave"}},{"type": "Feature", "geometry": { "type": "Point", "coordinates": [-75.447466,39.685235]}, "properties": { "type": 5, "address":""}},{"type": "Feature", "geometry": { "type": "Point", "coordinates": [-75.196985,40.134295]}, "properties": { "type": 5, "address":""}},{"type": "Feature", "geometry": { "type": "Point", "coordinates": [-75.149522,40.016918]}, "properties": { "type": 1, "address":"W Hunting Park Ave / N Broad St"}},{"type": "Feature", "geometry": { "type": "Point", "coordinates": [-75.120928,40.163517]}, "properties": { "type": 5, "address":""}},{"type": "Feature", "geometry": { "type": "Point", "coordinates": [-75.015383,40.123586]}, "properties": { "type": 1, "address":"Bustleton Ave / Byberry Rd"}},{"type": "Feature", "geometry": { "type": "Point", "coordinates": [-74.777391,40.096519]}, "properties": { "type": 5, "address":""}},{"type": "Feature", "geometry": { "type": "Point", "coordinates": [-74.248116,40.709218]}, "properties": { "type": 5, "address":""}},{"type": "Feature", "geometry": { "type": "Point", "coordinates": [-74.217395,40.739162]}, "properties": { "type": 5, "address":""}},{"type": "Feature", "geometry": { "type": "Point", "coordinates": [-74.1837,40.668895]}, "properties": { "type": 5, "address":""}},{"type": "Feature", "geometry": { "type": "Point", "coordinates": [-74.162371,40.604648]}, "properties": { "type": 1, "address":"Richmond Ave / Eton Pl"}},{"type": "Feature", "geometry": { "type": "Point", "coordinates": [-74.156508,40.70821]}, "properties": { "type": 5, "address":""}},{"type": "Feature", "geometry": { "type": "Point", "coordinates": [-74.097633,40.908444]}, "properties": { "type": 5, "address":""}},{"type": "Feature", "geometry": { "type": "Point", "coordinates": [-74.071287,40.979639]}, "properties": { "type": 5, "address":""}},{"type": "Feature", "geometry": { "type": "Point", "coordinates": [-74.060254,40.811785]}, "properties": { "type": 5, "address":""}},{"type": "Feature", "geometry": { "type": "Point", "coordinates": [-74.016987,40.607705]}, "properties": { "type": 1, "address":"14th Ave / Poly Pl"}},{"type": "Feature", "geometry": { "type": "Point", "coordinates": [-74.010672,40.729108]}, "properties": { "type": 1, "address":"W Houston St / Lincoln Hwy"}},{"type": "Feature", "geometry": { "type": "Point", "coordinates": [-74.000751,40.59877]}, "properties": { "type": 1, "address":"21st Ave / Cropsey Ave"}},{"type": "Feature", "geometry": { "type": "Point", "coordinates": [-74.001902,40.71939]}, "properties": { "type": 1, "address":"Broadway / Canal St"}},{"type": "Feature", "geometry": { "type": "Point", "coordinates": [-73.990869,40.70076]}, "properties": { "type": 1, "address":"Prospect St / Cadman Plz W"}},{"type": "Feature", "geometry": { "type": "Point", "coordinates": [-73.980723,40.64951]}, "properties": { "type": 1, "address":"McDonald Ave / Greenwood Ave"}},{"type": "Feature", "geometry": { "type": "Point", "coordinates": [-73.975118,40.680832]}, "properties": { "type": 1, "address":"Flatbush Ave / Bergen St"}},{"type": "Feature", "geometry": { "type": "Point", "coordinates": [-75.751675,39.658597]}, "properties": { "type": 1, "address":"Christina Pkwy / S College Ave"}},{"type": "Feature", "geometry": { "type": "Point", "coordinates": [-75.68018,39.675368]}, "properties": { "type": 1, "address":"State Rd 273 / S Gerald Dr"}},{"type": "Feature", "geometry": { "type": "Point", "coordinates": [-75.571069,39.745412]}, "properties": { "type": 1, "address":"Lancaster Ave / N Dupont St"}},{"type": "Feature", "geometry": { "type": "Point", "coordinates": [-75.551895,39.733832]}, "properties": { "type": 1, "address":"S Walnut St / A St"}},{"type": "Feature", "geometry": { "type": "Point", "coordinates": [-75.540894,39.75223]}, "properties": { "type": 1, "address":"N Market St / Concord Ave"}},{"type": "Feature", "geometry": { "type": "Point", "coordinates": [-75.240196,39.904054]}, "properties": { "type": 1, "address":"Island Ave / Lindbergh Blvd"}},{"type": "Feature", "geometry": { "type": "Point", "coordinates": [-75.046688,40.056647]}, "properties": { "type": 1, "address":"Rhawn St / E Roosevelt Blvd"}},{"type": "Feature", "geometry": { "type": "Point", "coordinates": [-75.01524,40.094694]}, "properties": { "type": 1, "address":"Red Lion Rd / Roosevelt Blvd"}},{"type": "Feature", "geometry": { "type": "Point", "coordinates": [-74.962925,40.128427]}, "properties": { "type": 5, "address":""}},{"type": "Feature", "geometry": { "type": "Point", "coordinates": [-74.302932,40.486649]}, "properties": { "type": 5, "address":""}},{"type": "Feature", "geometry": { "type": "Point", "coordinates": [-74.175149,40.850326]}, "properties": { "type": 5, "address":""}},{"type": "Feature", "geometry": { "type": "Point", "coordinates": [-74.169818,40.561092]}, "properties": { "type": 1, "address":"Richmond Ave / Arthur Kill Rd"}},{"type": "Feature", "geometry": { "type": "Point", "coordinates": [-74.157362,40.608048]}, "properties": { "type": 1, "address":"Victory Blvd / Morani St"}},{"type": "Feature", "geometry": { "type": "Point", "coordinates": [-74.124456,40.730781]}, "properties": { "type": 5, "address":""}},{"type": "Feature", "geometry": { "type": "Point", "coordinates": [-74.100224,40.90543]}, "properties": { "type": 5, "address":""}},{"type": "Feature", "geometry": { "type": "Point", "coordinates": [-74.066552,40.957825]}, "properties": { "type": 5, "address":""}},{"type": "Feature", "geometry": { "type": "Point", "coordinates": [-73.993939,40.664409]}, "properties": { "type": 1, "address":"18th St / 4th Ave"}},{"type": "Feature", "geometry": { "type": "Point", "coordinates": [-73.971264,40.583078]}, "properties": { "type": 4, "address":"Shore Pkwy S"}},{"type": "Feature", "geometry": { "type": "Point", "coordinates": [-75.709405,39.697861]}, "properties": { "type": 1, "address":"Kirkwood Hwy / Polly Drummond Hill Rd"}},{"type": "Feature", "geometry": { "type": "Point", "coordinates": [-75.562396,39.741861]}, "properties": { "type": 1, "address":"Lancaster Ave / S Jackson St"}},{"type": "Feature", "geometry": { "type": "Point", "coordinates": [-75.171775,40.138511]}, "properties": { "type": 5, "address":""}},{"type": "Feature", "geometry": { "type": "Point", "coordinates": [-75.094564,39.994679]}, "properties": { "type": 1, "address":"Castor Ave / Aramingo Ave"}},{"type": "Feature", "geometry": { "type": "Point", "coordinates": [-75.006972,40.118598]}, "properties": { "type": 1, "address":"Worthington Rd / Byberry Rd"}},{"type": "Feature", "geometry": { "type": "Point", "coordinates": [-74.141099,40.644111]}, "properties": { "type": 5, "address":""}},{"type": "Feature", "geometry": { "type": "Point", "coordinates": [-74.078472,40.803438]}, "properties": { "type": 5, "address":""}},{"type": "Feature", "geometry": { "type": "Point", "coordinates": [-74.009856,40.689278]}, "properties": { "type": 5, "address":""}},{"type": "Feature", "geometry": { "type": "Point", "coordinates": [-74.000948,40.640331]}, "properties": { "type": 1, "address":"9th Ave / 49th St"}},{"type": "Feature", "geometry": { "type": "Point", "coordinates": [-73.981839,40.752204]}, "properties": { "type": 1, "address":"W 40th St / 5th Ave"}},{"type": "Feature", "geometry": { "type": "Point", "coordinates": [-75.549698,39.737656]}, "properties": { "type": 1, "address":"N Walnut St / E 2nd St"}},{"type": "Feature", "geometry": { "type": "Point", "coordinates": [-75.534549,39.829742]}, "properties": { "type": 1, "address":"Shipley Rd / Naamans Rd"}},{"type": "Feature", "geometry": { "type": "Point", "coordinates": [-75.125448,40.02535]}, "properties": { "type": 1, "address":"N Mascher St / Roosevelt Blvd"}},{"type": "Feature", "geometry": { "type": "Point", "coordinates": [-75.069576,40.035277]}, "properties": { "type": 1, "address":"Levick St / Roosevelt Blvd"}},{"type": "Feature", "geometry": { "type": "Point", "coordinates": [-74.846656,40.121558]}, "properties": { "type": 5, "address":""}},{"type": "Feature", "geometry": { "type": "Point", "coordinates": [-74.184473,40.668716]}, "properties": { "type": 5, "address":""}},{"type": "Feature", "geometry": { "type": "Point", "coordinates": [-74.177907,40.829418]}, "properties": { "type": 5, "address":""}},{"type": "Feature", "geometry": { "type": "Point", "coordinates": [-74.168766,40.876927]}, "properties": { "type": 5, "address":""}},{"type": "Feature", "geometry": { "type": "Point", "coordinates": [-74.021212,40.618481]}, "properties": { "type": 1, "address":"7th Ave / 86th St"}},{"type": "Feature", "geometry": { "type": "Point", "coordinates": [-74.004916,40.757034]}, "properties": { "type": 1, "address":"W 34th St / Lincoln Hwy"}},{"type": "Feature", "geometry": { "type": "Point", "coordinates": [-73.987357,40.608164]}, "properties": { "type": 1, "address":"Bay Pkwy / 75th St"}},{"type": "Feature", "geometry": { "type": "Point", "coordinates": [-73.981432,40.613835]}, "properties": { "type": 1, "address":"65th St / Bay Pkwy"}},{"type": "Feature", "geometry": { "type": "Point", "coordinates": [-73.974408,40.644913]}, "properties": { "type": 1, "address":"Church Ave / Ocean Pkwy"}},{"type": "Feature", "geometry": { "type": "Point", "coordinates": [-75.77598,39.665489]}, "properties": { "type": 1, "address":"Christina Pkwy / Elkton Rd"}},{"type": "Feature", "geometry": { "type": "Point", "coordinates": [-75.589552,39.739229]}, "properties": { "type": 1, "address":"S Dupont Rd / Wilmington Ave"}},{"type": "Feature", "geometry": { "type": "Point", "coordinates": [-75.56079,39.74219]}, "properties": { "type": 1, "address":"W 2nd St / N Adams St"}},{"type": "Feature", "geometry": { "type": "Point", "coordinates": [-75.139862,40.021334]}, "properties": { "type": 1, "address":"N 9th St / Roosevelt Blvd"}},{"type": "Feature", "geometry": { "type": "Point", "coordinates": [-75.048753,39.977107]}, "properties": { "type": 5, "address":""}},{"type": "Feature", "geometry": { "type": "Point", "coordinates": [-74.338464,40.525001]}, "properties": { "type": 5, "address":""}},{"type": "Feature", "geometry": { "type": "Point", "coordinates": [-74.246421,40.703488]}, "properties": { "type": 5, "address":""}},{"type": "Feature", "geometry": { "type": "Point", "coordinates": [-74.166576,40.627368]}, "properties": { "type": 1, "address":"Forest Ave / South Ave"}},{"type": "Feature", "geometry": { "type": "Point", "coordinates": [-74.158774,40.612984]}, "properties": { "type": 1, "address":"Richmond Ave / Lander Ave"}},{"type": "Feature", "geometry": { "type": "Point", "coordinates": [-74.1052,40.618281]}, "properties": { "type": 1, "address":"Clove Rd / Cheshire Pl"}},{"type": "Feature", "geometry": { "type": "Point", "coordinates": [-74.008074,40.749312]}, "properties": { "type": 1, "address":"11th Ave / W 23rd St"}},{"type": "Feature", "geometry": { "type": "Point", "coordinates": [-73.982864,40.766734]}, "properties": { "type": 1, "address":"8th Ave / W 57th St"}},{"type": "Feature", "geometry": { "type": "Point", "coordinates": [-73.969206,40.672784]}, "properties": { "type": 1, "address":"Plaza St E / Grand Army Plz"}},{"type": "Feature", "geometry": { "type": "Point", "coordinates": [-75.570661,39.748311]}, "properties": { "type": 1, "address":"W 4th St / N Scott St"}},{"type": "Feature", "geometry": { "type": "Point", "coordinates": [-75.531885,39.756265]}, "properties": { "type": 1, "address":"N Market St / W 30th St"}},{"type": "Feature", "geometry": { "type": "Point", "coordinates": [-75.352304,39.810075]}, "properties": { "type": 5, "address":""}},{"type": "Feature", "geometry": { "type": "Point", "coordinates": [-75.121102,39.975305]}, "properties": { "type": 1, "address":"E York St / N Delaware Ave"}},{"type": "Feature", "geometry": { "type": "Point", "coordinates": [-75.115012,40.134794]}, "properties": { "type": 1, "address":"York Rd / Welsh Rd"}},{"type": "Feature", "geometry": { "type": "Point", "coordinates": [-75.007253,40.069228]}, "properties": { "type": 1, "address":"Academy Rd / Grant Ave"}},{"type": "Feature", "geometry": { "type": "Point", "coordinates": [-74.789399,40.101463]}, "properties": { "type": 5, "address":""}},{"type": "Feature", "geometry": { "type": "Point", "coordinates": [-74.207759,40.755735]}, "properties": { "type": 5, "address":""}},{"type": "Feature", "geometry": { "type": "Point", "coordinates": [-74.165684,40.87827]}, "properties": { "type": 5, "address":""}},{"type": "Feature", "geometry": { "type": "Point", "coordinates": [-74.156207,40.708756]}, "properties": { "type": 5, "address":""}},{"type": "Feature", "geometry": { "type": "Point", "coordinates": [-74.116378,40.563908]}, "properties": { "type": 1, "address":"Hylan Blvd / Tysens Ln"}},{"type": "Feature", "geometry": { "type": "Point", "coordinates": [-74.119823,40.575846]}, "properties": { "type": 1, "address":"Richmond Rd / New Dorp Ln"}},{"type": "Feature", "geometry": { "type": "Point", "coordinates": [-74.059771,40.811182]}, "properties": { "type": 5, "address":""}},{"type": "Feature", "geometry": { "type": "Point", "coordinates": [-74.021384,40.727502]}, "properties": { "type": 5, "address":""}},{"type": "Feature", "geometry": { "type": "Point", "coordinates": [-74.007343,40.651511]}, "properties": { "type": 1, "address":"4th Ave / 41st St"}},{"type": "Feature", "geometry": { "type": "Point", "coordinates": [-74.001212,40.762027]}, "properties": { "type": 1, "address":"W 42nd St / Lincoln Hwy"}},{"type": "Feature", "geometry": { "type": "Point", "coordinates": [-73.990509,40.643161]}, "properties": { "type": 1, "address":"Fort Hamilton Pkwy / 39th St"}},{"type": "Feature", "geometry": { "type": "Point", "coordinates": [-73.988645,40.722967]}, "properties": { "type": 1, "address":"1st Ave / E Houston St"}},{"type": "Feature", "geometry": { "type": "Point", "coordinates": [-73.987265,40.622019]}, "properties": { "type": 1, "address":"18th Ave / 60th St"}},{"type": "Feature", "geometry": { "type": "Point", "coordinates": [-73.981119,40.65161]}, "properties": { "type": 1, "address":"McDonald Ave / Vanderbilt St"}},{"type": "Feature", "geometry": { "type": "Point", "coordinates": [-73.978797,40.753498]}, "properties": { "type": 1, "address":"E 43rd St / Madison Ave"}},{"type": "Feature", "geometry": { "type": "Point", "coordinates": [-73.97597,40.776234]}, "properties": { "type": 1, "address":"Central Park W / 72nd St Transverse"}},{"type": "Feature", "geometry": { "type": "Point", "coordinates": [-75.545361,39.696313]}, "properties": { "type": 5, "address":""}},{"type": "Feature", "geometry": { "type": "Point", "coordinates": [-74.299936,40.540114]}, "properties": { "type": 5, "address":""}},{"type": "Feature", "geometry": { "type": "Point", "coordinates": [-74.123125,40.754163]}, "properties": { "type": 5, "address":""}},{"type": "Feature", "geometry": { "type": "Point", "coordinates": [-74.090116,40.609412]}, "properties": { "type": 1, "address":"Narrows Rd N / Richmond Rd"}},{"type": "Feature", "geometry": { "type": "Point", "coordinates": [-74.008786,40.742445]}, "properties": { "type": 1, "address":"Lincoln Hwy / W 14th St"}},{"type": "Feature", "geometry": { "type": "Point", "coordinates": [-73.973457,40.574802]}, "properties": { "type": 1, "address":"Surf Ave / W 5th St"}},{"type": "Feature", "geometry": { "type": "Point", "coordinates": [-73.970365,40.79406]}, "properties": { "type": 1, "address":"Amsterdam Ave / W 96th St"}},{"type": "Feature", "geometry": { "type": "Point", "coordinates": [-73.999155,40.75459]}, "properties": { "type": 1, "address":"W 34th St / 10th Ave"}},{"type": "Feature", "geometry": { "type": "Point", "coordinates": [-74.162426,40.607195]}, "properties": { "type": 1, "address":"Victory Blvd / Richmond Ave"}},{"type": "Feature", "geometry": { "type": "Point", "coordinates": [-74.221794,39.863298]}, "properties": { "type": 5, "address":""}},{"type": "Feature", "geometry": { "type": "Point", "coordinates": [-74.205834,39.99765]}, "properties": { "type": 5, "address":""}},{"type": "Feature", "geometry": { "type": "Point", "coordinates": [-74.166695,40.053032]}, "properties": { "type": 5, "address":""}},{"type": "Feature", "geometry": { "type": "Point", "coordinates": [-74.162618,40.063247]}, "properties": { "type": 5, "address":""}},{"type": "Feature", "geometry": { "type": "Point", "coordinates": [-74.139245,40.102418]}, "properties": { "type": 5, "address":""}},{"type": "Feature", "geometry": { "type": "Point", "coordinates": [-74.101308,40.339808]}, "properties": { "type": 5, "address":""}},{"type": "Feature", "geometry": { "type": "Point", "coordinates": [-74.206005,40.421554]}, "properties": { "type": 5, "address":""}},{"type": "Feature", "geometry": { "type": "Point", "coordinates": [-74.50579,40.264025]}, "properties": { "type": 5, "address":""}},{"type": "Feature", "geometry": { "type": "Point", "coordinates": [-75.074794,39.86158]}, "properties": { "type": 5, "address":""}},{"type": "Feature", "geometry": { "type": "Point", "coordinates": [-75.16374,39.951645]}, "properties": { "type": 1, "address":"S Penn Sq / Broad St"}},{"type": "Feature", "geometry": { "type": "Point", "coordinates": [-75.162465,39.957655]}, "properties": { "type": 1, "address":"Vine St / N Broad St"}},{"type": "Feature", "geometry": { "type": "Point", "coordinates": [-74.686621,39.513629]}, "properties": { "type": 5, "address":""}},{"type": "Feature", "geometry": { "type": "Point", "coordinates": [-74.234512,39.793492]}, "properties": { "type": 5, "address":""}},{"type": "Feature", "geometry": { "type": "Point", "coordinates": [-74.212915,39.905961]}, "properties": { "type": 5, "address":""}},{"type": "Feature", "geometry": { "type": "Point", "coordinates": [-74.164034,40.063978]}, "properties": { "type": 5, "address":""}},{"type": "Feature", "geometry": { "type": "Point", "coordinates": [-74.081615,40.250401]}, "properties": { "type": 5, "address":""}},{"type": "Feature", "geometry": { "type": "Point", "coordinates": [-74.143488,40.372715]}, "properties": { "type": 5, "address":""}},{"type": "Feature", "geometry": { "type": "Point", "coordinates": [-74.955661,39.931055]}, "properties": { "type": 5, "address":""}},{"type": "Feature", "geometry": { "type": "Point", "coordinates": [-75.171337,39.916837]}, "properties": { "type": 1, "address":"Oregon Ave / Broad St"}},{"type": "Feature", "geometry": { "type": "Point", "coordinates": [-74.23919,39.795075]}, "properties": { "type": 5, "address":""}},{"type": "Feature", "geometry": { "type": "Point", "coordinates": [-74.083525,40.284898]}, "properties": { "type": 5, "address":""}},{"type": "Feature", "geometry": { "type": "Point", "coordinates": [-74.478185,40.349168]}, "properties": { "type": 5, "address":""}},{"type": "Feature", "geometry": { "type": "Point", "coordinates": [-74.206992,39.996639]}, "properties": { "type": 5, "address":""}},{"type": "Feature", "geometry": { "type": "Point", "coordinates": [-74.102789,40.3378]}, "properties": { "type": 5, "address":""}},{"type": "Feature", "geometry": { "type": "Point", "coordinates": [-75.198162,39.939629]}, "properties": { "type": 1, "address":"Grays Ferry Ave / S 34th St"}},{"type": "Feature", "geometry": { "type": "Point", "coordinates": [-75.118658,39.948544]}, "properties": { "type": 5, "address":""}},{"type": "Feature", "geometry": { "type": "Point", "coordinates": [-74.211284,39.893665]}, "properties": { "type": 5, "address":""}},{"type": "Feature", "geometry": { "type": "Point", "coordinates": [-74.214996,40.421276]}, "properties": { "type": 5, "address":""}},{"type": "Feature", "geometry": { "type": "Point", "coordinates": [-75.163669,39.953486]}, "properties": { "type": 1, "address":"N Broad St / John F Kennedy Blvd"}},{"type": "Feature", "geometry": { "type": "Point", "coordinates": [-75.15452,39.909695]}, "properties": { "type": 5, "address":""}},{"type": "Feature", "geometry": { "type": "Point", "coordinates": [-74.680298,39.507293]}, "properties": { "type": 5, "address":""}},{"type": "Feature", "geometry": { "type": "Point", "coordinates": [-74.150586,40.375167]}, "properties": { "type": 5, "address":""}},{"type": "Feature", "geometry": { "type": "Point", "coordinates": [-74.138939,40.101589]}, "properties": { "type": 5, "address":""}},{"type": "Feature", "geometry": { "type": "Point", "coordinates": [-74.245238,39.774546]}, "properties": { "type": 5, "address":""}},{"type": "Feature", "geometry": { "type": "Point", "coordinates": [-75.237455,39.95843]}, "properties": { "type": 1, "address":"Walnut St / S 58th St"}},{"type": "Feature", "geometry": { "type": "Point", "coordinates": [-74.463122,39.554907]}, "properties": { "type": 5, "address":""}},{"type": "Feature", "geometry": { "type": "Point", "coordinates": [-74.218171,39.864451]}, "properties": { "type": 5, "address":""}},{"type": "Feature", "geometry": { "type": "Point", "coordinates": [-74.170053,40.055732]}, "properties": { "type": 5, "address":""}},{"type": "Feature", "geometry": { "type": "Point", "coordinates": [-74.980273,39.708356]}, "properties": { "type": 5, "address":""}},{"type": "Feature", "geometry": { "type": "Point", "coordinates": [-74.979023,39.710061]}, "properties": { "type": 5, "address":""}},{"type": "Feature", "geometry": { "type": "Point", "coordinates": [-74.892753,39.667555]}, "properties": { "type": 5, "address":""}},{"type": "Feature", "geometry": { "type": "Point", "coordinates": [-74.889939,39.66714]}, "properties": { "type": 5, "address":""}},{"type": "Feature", "geometry": { "type": "Point", "coordinates": [-73.988617,41.319964]}, "properties": { "type": 5, "address":""}},{"type": "Feature", "geometry": { "type": "Point", "coordinates": [-74.128206,41.313837]}, "properties": { "type": 5, "address":""}},{"type": "Feature", "geometry": { "type": "Point", "coordinates": [-73.970925,40.626551]}, "properties": { "type": 1, "address":"Ocean Pkwy / Ave I"}},{"type": "Feature", "geometry": { "type": "Point", "coordinates": [-73.972159,40.633106]}, "properties": { "type": 1, "address":"Ocean Pkwy / 18th Ave"}},{"type": "Feature", "geometry": { "type": "Point", "coordinates": [-73.994915,40.621991]}, "properties": { "type": 1, "address":"65th St / 16th Ave"}},{"type": "Feature", "geometry": { "type": "Point", "coordinates": [-73.991051,40.723652]}, "properties": { "type": 1, "address":"E Houston St / Chrystie St"}},{"type": "Feature", "geometry": { "type": "Point", "coordinates": [-73.989978,40.767198]}, "properties": { "type": 1, "address":"W 54th St / 10th Ave"}},{"type": "Feature", "geometry": { "type": "Point", "coordinates": [-74.1558,40.563729]}, "properties": { "type": 1, "address":"Giffords Ln / Arthur Kill Rd"}},{"type": "Feature", "geometry": { "type": "Point", "coordinates": [-74.110019,40.620709]}, "properties": { "type": 1, "address":"Bement Ave / Clove Rd"}},{"type": "Feature", "geometry": { "type": "Point", "coordinates": [-75.034885,40.074398]}, "properties": { "type": 1, "address":"Welsh Rd / Roosevelt Blvd"}},{"type": "Feature", "geometry": { "type": "Point", "coordinates": [-74.97185,40.086837]}, "properties": { "type": 1, "address":"Normandy Dr / Knights Rd"}},{"type": "Feature", "geometry": { "type": "Point", "coordinates": [-75.054653,40.044653]}, "properties": { "type": 1, "address":"Cottman Ave / Roosevelt Blvd"}},{"type": "Feature", "geometry": { "type": "Point", "coordinates": [-75.162368,39.958071]}, "properties": { "type": 1, "address":"Vine St / N Broad St"}},{"type": "Feature", "geometry": { "type": "Point", "coordinates": [-75.546538,39.742306]}, "properties": { "type": 1, "address":"E 8th St / N Walnut St"}},{"type": "Feature", "geometry": { "type": "Point", "coordinates": [-75.552557,39.740924]}, "properties": { "type": 1, "address":"W 4th St / N Orange St"}},{"type": "Feature", "geometry": { "type": "Point", "coordinates": [-75.555265,39.742031]}, "properties": { "type": 1, "address":"W 4th St / N Washington St"}},{"type": "Feature", "geometry": { "type": "Point", "coordinates": [-75.559678,39.743827]}, "properties": { "type": 1, "address":"N Adams St / W 4th St"}},{"type": "Feature", "geometry": { "type": "Point", "coordinates": [-75.556535,39.752502]}, "properties": { "type": 1, "address":"Pennsylvania Ave / N Van Buren St"}},{"type": "Feature", "geometry": { "type": "Point", "coordinates": [-75.55895,39.753173]}, "properties": { "type": 1, "address":"Pennsylvania Ave / N Franklin St"}},{"type": "Feature", "geometry": { "type": "Point", "coordinates": [-75.567114,39.755696]}, "properties": { "type": 1, "address":"N Lincoln St / Pennsylvania Ave"}},{"type": "Feature", "geometry": { "type": "Point", "coordinates": [-75.568912,39.753052]}, "properties": { "type": 1, "address":"N Lincoln St / W 9th St"}},{"type": "Feature", "geometry": { "type": "Point", "coordinates": [-75.584797,39.750992]}, "properties": { "type": 1, "address":"Lancaster Ave / N Cleveland Ave"}},{"type": "Feature", "geometry": { "type": "Point", "coordinates": [-75.571572,39.735644]}, "properties": { "type": 1, "address":"Maryland Ave / 7th Ave"}},{"type": "Feature", "geometry": { "type": "Point", "coordinates": [-75.630634,39.736041]}, "properties": { "type": 1, "address":"Newport Gap Pike / Kirkwood Hwy"}},{"type": "Feature", "geometry": { "type": "Point", "coordinates": [-75.54539,39.727074]}, "properties": { "type": 1, "address":"D St / S Heald St"}},{"type": "Feature", "geometry": { "type": "Point", "coordinates": [-75.584676,39.6867]}, "properties": { "type": 1, "address":"Roosevelt Ave / E Roosevelt Ave"}},{"type": "Feature", "geometry": { "type": "Point", "coordinates": [-75.65288,39.688275]}, "properties": { "type": 1, "address":"Geoffrey Dr / Churchmans Rd"}},{"type": "Feature", "geometry": { "type": "Point", "coordinates": [-75.699752,39.700967]}, "properties": { "type": 1, "address":"Harmony Rd N / Harmony Rd S"}},{"type": "Feature", "geometry": { "type": "Point", "coordinates": [-75.697733,39.648417]}, "properties": { "type": 1, "address":"Salem Woods Rd / Old Baltimore Pike"}},{"type": "Feature", "geometry": { "type": "Point", "coordinates": [-75.655014,39.660064]}, "properties": { "type": 1, "address":"E Main St / Christiana Rd"}},{"type": "Feature", "geometry": { "type": "Point", "coordinates": [-76.357376,39.528256]}, "properties": { "type": 1, "address":"Boulton St / State Hwy 24"}}]}