{ "type": "FeatureCollection", "features": [{"type": "Feature", "geometry": { "type": "Point", "coordinates": [-88.563736,39.137048]}, "properties": { "name": "Effingham, IL", "dateOpened": "2015-03-28", "elevationMeters": "184", "locationId": "effinghamilsupercharger", "stallCount": "6"}},{"type": "Feature", "geometry": { "type": "Point", "coordinates": [-88.259884,40.146209]}, "properties": { "name": "Champaign, IL", "dateOpened": "2016-03-23", "elevationMeters": "228", "locationId": "champaignillinoissupercharger", "stallCount": "8"}},{"type": "Feature", "geometry": { "type": "Point", "coordinates": [-87.331737,39.443345]}, "properties": { "name": "Terre Haute, IN", "dateOpened": "2016-03-30", "elevationMeters": "171", "locationId": "terrehautesupercharger", "stallCount": "8"}}]}